{
    "i18n": true,
    "type": "panel",
    "items": {
        "serverURL": {
            "type": "text",
            "label": "serverURL",
            "help": "URL without Topic - https://ntfy-server.sh",
            "newLine": true
        },
        "defaultTopic": {
            "type": "text",
            "label": "defaultTopic",
            "newLine": true
        },
        "defaultUsername": {
            "type": "text",
            "label": "defaultUsername",
            "newLine": true
        },
        "defaultPassword": {
            "type": "text",
            "label": "defaultPassword",
            "newLine": true
        },
        "defaultAccessToken": {
            "type": "text",
            "label": "defaultAccessToken",
            "help": "Only if username/password is not used",
            "newLine": true
        }
    }
}